examples/create_mdl.py
examples/device_response.py
examples/generate_device_key.py
examples/generate_issuer_cert.py
examples/utils.py
examples/verify_mdoc.py
isomdoc/__init__.py
isomdoc/py.typed
isomdoc/create/__init__.py
isomdoc/create/create_mdoc.py
isomdoc/internal/__init__.py
isomdoc/internal/exceptions.py
isomdoc/internal/helpers.py
isomdoc/internal/types.py
isomdoc/verify/__init__.py
isomdoc/verify/verify_mdoc.py
tests/__init__.py
tests/create_test.py
isomdoc-0.0.3.dist-info/LICENSE
isomdoc-0.0.3.dist-info/METADATA
isomdoc-0.0.3.dist-info/WHEEL
isomdoc-0.0.3.dist-info/top_level.txt
isomdoc-0.0.3.dist-info/RECORD
