Metadata-Version: 2.1
Name: isomdoc
Version: 0.0.3
Summary: A python module to create and verify ISO mdocs
Author-email: Lee Campbell <leecam@google.com>
License: Apache License
Project-URL: Homepage, https://github.com/leecam/pymdoc
Project-URL: Repository, https://github.com/leecam/pymdoc.git
Project-URL: Issues, https://github.com/leecam/pymdoc/issues
Classifier: Programming Language :: Python :: 3
Classifier: Operating System :: OS Independent
Requires-Python: >=3.8
License-File: LICENSE
Requires-Dist: cbor2
Requires-Dist: cryptography
